LICENSE
MANIFEST.in
README.rst
pytest.ini
requirements.txt
setup.py
Avena.egg-info/PKG-INFO
Avena.egg-info/SOURCES.txt
Avena.egg-info/dependency_links.txt
Avena.egg-info/requires.txt
Avena.egg-info/top_level.txt
avena/__init__.py
avena/avena.py
avena/filter.py
avena/flip.py
avena/image.py
avena/interp.py
avena/logistic.py
avena/map.py
avena/np.py
avena/tile.py
avena/translate.py
avena/utils.py
avena/video.py
avena/xcor2.py
scripts/avena