Metadata-Version: 1.1
Name: Avena
Version: 1.7
Summary: Avena is an image processing library and command-line tool.
Home-page: https://bitbucket.org/eliteraspberries/avena
Author: Mansour Moufid
Author-email: mansourmoufid@gmail.com
License: ISC
Platform: UNKNOWN
Classifier: Development Status :: 4 - Beta
Classifier: Environment :: Console
Classifier: Intended Audience :: End Users/Desktop
Classifier: License :: OSI Approved :: ISC License (ISCL)
Classifier: Operating System :: OS Independent
Classifier: Programming Language :: Python
Classifier: Topic :: Multimedia :: Graphics
